thresholdclustering/__init__.py
thresholdclustering/thresholdclustering.py
thresholdclustering-1.1.dist-info/LICENSE
thresholdclustering-1.1.dist-info/METADATA
thresholdclustering-1.1.dist-info/WHEEL
thresholdclustering-1.1.dist-info/top_level.txt
thresholdclustering-1.1.dist-info/RECORD
