Metadata-Version: 2.1
Name: thresholdclustering
Version: 1.1
Summary: Community detection for directed, weighted networkX graphs with spectral thresholding.
Home-page: https://github.com/IngoMarquart/python-threshold-clustering
Author: Ingo Marquart
Author-email: ingo.marquart@esmt.org
License: MIT
Download-URL: https://pypi.org/project/thresholdclustering
Keywords: community detection,clustering,networkx,python-louvain
Platform: UNKNOWN
